{
  "source": "edicao_MjY2MTc5.pdf",
  "date": "2022-07",
  "pages": [
    {
      "page": 1,
      "text": "SEMANÁRIO\nOficial Eletrônico\navare.sp.gov.br\nTerça-feira, 05 de julho de 2022 Ano VI | Edição nº 1328 Prefeito: Joselyr B. Costa Silvestre\nSec. Mun. de Ind., Com., Ciência e Tecnologia\nPODER EXECUTIVO\nJUSTIFICATIVA\nPoder Executivo\n(inversão de ordem cronológica de pagamento)\nAtos Oficiais\nNos termos do art. 5º da Lei Federal nº. 8.666/93 e\nAtos Oficiais\nLeis instrução 02/95 item II e aditamento 01/97 do Tribunal de\nContas do Estado, vem justificar a necessidade de alteração\nLeis Lei n° 2.698, de 05 de julho de 2022. da ordem cronológica de pagamentos por se tratar de\naquisição de gases medicinais e tal quebra de ordem\n(Altera a Lei nº 2601/2022 da\ncronológica se faz necessária para atendimento da\nCâmara de Vereadores da\ndemanda da Secretaria de Saúde.\nEstância Turística de Avaré e dá\nFornecedor: White Martins Gases Industriais Ltda.\noutras providências.)\nEmpenho(s): 1062,1063/2022\nValor: R$ 5.443,20\nAutoria: Mesa Diretora (Projeto de Lei nº\nAvaré, 05 de julho de 2022\n159/2022)\nRoslindo Wilson Machado\nJOSELYR BENEDITO COSTA SILVESTRE, Prefeito da\nSecretário Municipal de Saúde\nEstância Turística de Avaré, usando das atribuições que lhe\nJUSTIFICATIVA\nsão conferidas por lei,\n(inversão de ordem cronológica de pagamento)\nFaço saber que a Câmara Municipal da Estância\nNos termos do art. 5º da Lei Federal nº. 8.666/93 e\nTurística de Avaré aprovou e eu sanciono e promulgo a\ninstrução 02/95 item II e aditamento 01/97 do Tribunal de\nseguinte Lei:\nContas do Estado, vem justificar a necessidade de alteração\nArt. 1º - o Artigo 1º da Lei nº 2601/2022 passa a\nda ordem cronológica de pagamentos por se tratar de\nvigorar com a seguinte redação:\ncontratação de empresa especializada para serviços de\nArt. 1º - (...)\nmonitoramento de alarme e câmera e tal quebra de ordem\nParágrafo Único - (...)\ncronológica se faz necessária para atender a Secretaria\nI - Fica autorizada a Câmara de Vereadores da\nMunicipal de Governo.\nEstância Turística de Avaré a conceder abono de\nFornecedor: Service Tecnologia em Segurança Ltda\nNatal a todos os seus servidores a ser concedido em\nEmpenho(s):5701/2022\npecúnia e/ou em cesta com produtos alimentícios e\nValor: R$ 2.028,00\nnatalinos, através de Ato da Mesa.\nAvaré, 05 de julho de 2022\nArt. 2º - Esta lei entrará em vigor na data da sua\nPatricia de Cassia Furno Olindo Franzolin\npublicação.\nSecretária Municipal de Governo\nPrefeitura da Estância Turística de Avaré, 05 de julho de\nJUSTIFICATIVA\n2022.\n(inversão de ordem cronológica de pagamento)\nJoselyr Benedito Costa Silvestre\nNos termos do art. 5º da Lei Federal nº. 8.666/93 e\nPrefeito\ninstrução 02/95 item II e aditamento 01/97 do Tribunal de\n...........................................................................................................\nContas do Estado, vem justificar a necessidade de alteração\nContas Públicas e Instrumentos de Gestão Fiscal\nda ordem cronológica de pagamentos por se tratar de\nContas Públicas e Instrumentos de Gestão Fiscal contratação de empresa especializada para serviços de\nQuebra de Ordem Cronológica\nmonitoramento de alarme e câmera e tal quebra de ordem\nQuebra de Ordem Cronológica PREFEITURA DA ESTÂNCIA TURÍSTICA DE AVARÉ cronológica se faz necessária para atender a Procuradoria\nGeral do Município.\nJUSTIFICATIVA\nFornecedor: Service Tecnologia em Segurança Ltda\n(inversão de ordem cronológica de pagamento)\nEmpenho(s): 5692/2022\nNos termos do art. 5º da Lei Federal nº. 8.666/93 e\nValor: R$ 2.028,00\ninstrução 02/95 item II e aditamento 01/97 do Tribunal de\nAvaré, 05 de julho de 2022\nContas do Estado, vem justificar a necessidade de alteração\nJoselyr Benedito Costa Silvestre\nda ordem cronológica de pagamentos por se tratar de\nPrefeito Municipal\nfornecimento de materiais de limpeza, tal quebra de ordem\nJUSTIFICATIVA\ncronológica se faz necessária para atender a Casa do\n(inversão de ordem cronológica de pagamento)\nCidadão.\nNos termos do art. 5º da Lei Federal nº. 8.666/93 e\nFornecedor: Indústria e Comércio de Produtos de\ninstrução 02/95 item II e aditamento 01/97 do Tribunal de\nLimpeza Macatuba Ltda Me\nContas do Estado, vem justificar a necessidade de alteração\nEmpenho(s): 10572/2022\nda ordem cronológica de pagamentos por se tratar de\nValor: R$ 2.003,54\naquisição de material de informática, tal quebra de ordem\nAvaré, 05 de julho de 2022\ncronológica se faz necessária para atender aos serviços\nSandra de Fátima Theodoro\n1\nEstância Turística de Avaré – Estado de São Paulo\nInstituído pela Lei nº 37, de 28 de março de 2001 e Decreto nº 5.057, de 03 de janeiro de 2018\nSemanário Oficial assinado digitalmente conforme MP nº 2.200-2, de 2001, garantindo autenticidade, validade jurídica e integridade."
    },
    {
      "page": 2,
      "text": "SEMANÁRIO\nOficial Eletrônico\navare.sp.gov.br\nTerça-feira, 05 de julho de 2022 Ano VI | Edição nº 1328 Prefeito: Joselyr B. Costa Silvestre\nadministrativos.\nFornecedor: Megadata Indústria e Comércio de\nProdutos\nEmpenho(s): 10434/2022\nValor: R$ 245,00\nAvaré, 05 de julho de 2022\nPatricia de Cassia Furno Olindo Franzolin\nSecretária Municipal de Governo\nJUSTIFICATIVA\n(inversão de ordem cronológica de pagamento)\nNos termos do art. 5º da Lei Federal nº. 8.666/93 e\ninstrução 02/95 item II e aditamento 01/97 do Tribunal de\nContas do Estado, vem justificar a necessidade de alteração\nda ordem cronológica de pagamentos por se tratar de\naquisição de peças para veículo e tal quebra de ordem\ncronológica se faz necessária para manutenção da frota\nmunicipal.\nFornecedor: C. R. Service e Comércio de Produtos e\nPeças em Geral Eireli\nEmpenho(s): 10614,10616,10848,10880/2022\nValor: R$ 10.637,88\nAvaré, 05 de julho de 2022\nCesar Augusto Luciano Franco Morelli\nSecretário Municipal de Transportes e Serviços\nJUSTIFICATIVA\n(inversão de ordem cronológica de pagamento)\nNos termos do art. 5º da Lei Federal nº. 8.666/93 e\ninstrução 02/95 item II e aditamento 01/97 do Tribunal de\nContas do Estado, vem justificar a necessidade de alteração\nda ordem cronológica de pagamentos por se tratar de\naquisição de porta naval com fechadura e ferragens e tal\nquebra de ordem cronológica se faz necessária para\natender as necessidades do Departamento de\nContabilidade.\nFornecedor: Diego Leone\nEmpenho(s): 10849/2022\nValor: R$ 850,00\nAvaré, 05 de julho de 2022\nItamar de Araujo\nSecretário Municipal da Fazenda\nJUSTIFICATIVA\n(inversão de ordem cronológica de pagamento)\nNos termos do art. 5º da Lei Federal nº. 8.666/93 e\ninstrução 02/95 item II e aditamento 01/97 do Tribunal de\nContas do Estado, vem justificar a necessidade de alteração\nda ordem cronológica de pagamentos por se tratar de\naquisição de peças para veículo e tal quebra de ordem\ncronológica se faz necessária para manutenção de veículos\nda frota municipal.\nFornecedor: Chaguri Automotiva Eireli ME\nEmpenho(s): 13127,13128,13129,13130,13131/2022\nValor: R$ 16.211,80\nAvaré, 05 de julho de 2022\nCesar Augusto Luciano Franco Morelli\nSecretário Municipal de Transportes e Serviços\n...........................................................................................................\n2\nEstância Turística de Avaré – Estado de São Paulo\nInstituído pela Lei nº 37, de 28 de março de 2001 e Decreto nº 5.057, de 03 de janeiro de 2018\nSemanário Oficial assinado digitalmente conforme MP nº 2.200-2, de 2001, garantindo autenticidade, validade jurídica e integridade."
    }
  ],
  "full_text": "SEMANÁRIO\nOficial Eletrônico\navare.sp.gov.br\nTerça-feira, 05 de julho de 2022 Ano VI | Edição nº 1328 Prefeito: Joselyr B. Costa Silvestre\nSec. Mun. de Ind., Com., Ciência e Tecnologia\nPODER EXECUTIVO\nJUSTIFICATIVA\nPoder Executivo\n(inversão de ordem cronológica de pagamento)\nAtos Oficiais\nNos termos do art. 5º da Lei Federal nº. 8.666/93 e\nAtos Oficiais\nLeis instrução 02/95 item II e aditamento 01/97 do Tribunal de\nContas do Estado, vem justificar a necessidade de alteração\nLeis Lei n° 2.698, de 05 de julho de 2022. da ordem cronológica de pagamentos por se tratar de\naquisição de gases medicinais e tal quebra de ordem\n(Altera a Lei nº 2601/2022 da\ncronológica se faz necessária para atendimento da\nCâmara de Vereadores da\ndemanda da Secretaria de Saúde.\nEstância Turística de Avaré e dá\nFornecedor: White Martins Gases Industriais Ltda.\noutras providências.)\nEmpenho(s): 1062,1063/2022\nValor: R$ 5.443,20\nAutoria: Mesa Diretora (Projeto de Lei nº\nAvaré, 05 de julho de 2022\n159/2022)\nRoslindo Wilson Machado\nJOSELYR BENEDITO COSTA SILVESTRE, Prefeito da\nSecretário Municipal de Saúde\nEstância Turística de Avaré, usando das atribuições que lhe\nJUSTIFICATIVA\nsão conferidas por lei,\n(inversão de ordem cronológica de pagamento)\nFaço saber que a Câmara Municipal da Estância\nNos termos do art. 5º da Lei Federal nº. 8.666/93 e\nTurística de Avaré aprovou e eu sanciono e promulgo a\ninstrução 02/95 item II e aditamento 01/97 do Tribunal de\nseguinte Lei:\nContas do Estado, vem justificar a necessidade de alteração\nArt. 1º - o Artigo 1º da Lei nº 2601/2022 passa a\nda ordem cronológica de pagamentos por se tratar de\nvigorar com a seguinte redação:\ncontratação de empresa especializada para serviços de\nArt. 1º - (...)\nmonitoramento de alarme e câmera e tal quebra de ordem\nParágrafo Único - (...)\ncronológica se faz necessária para atender a Secretaria\nI - Fica autorizada a Câmara de Vereadores da\nMunicipal de Governo.\nEstância Turística de Avaré a conceder abono de\nFornecedor: Service Tecnologia em Segurança Ltda\nNatal a todos os seus servidores a ser concedido em\nEmpenho(s):5701/2022\npecúnia e/ou em cesta com produtos alimentícios e\nValor: R$ 2.028,00\nnatalinos, através de Ato da Mesa.\nAvaré, 05 de julho de 2022\nArt. 2º - Esta lei entrará em vigor na data da sua\nPatricia de Cassia Furno Olindo Franzolin\npublicação.\nSecretária Municipal de Governo\nPrefeitura da Estância Turística de Avaré, 05 de julho de\nJUSTIFICATIVA\n2022.\n(inversão de ordem cronológica de pagamento)\nJoselyr Benedito Costa Silvestre\nNos termos do art. 5º da Lei Federal nº. 8.666/93 e\nPrefeito\ninstrução 02/95 item II e aditamento 01/97 do Tribunal de\n...........................................................................................................\nContas do Estado, vem justificar a necessidade de alteração\nContas Públicas e Instrumentos de Gestão Fiscal\nda ordem cronológica de pagamentos por se tratar de\nContas Públicas e Instrumentos de Gestão Fiscal contratação de empresa especializada para serviços de\nQuebra de Ordem Cronológica\nmonitoramento de alarme e câmera e tal quebra de ordem\nQuebra de Ordem Cronológica PREFEITURA DA ESTÂNCIA TURÍSTICA DE AVARÉ cronológica se faz necessária para atender a Procuradoria\nGeral do Município.\nJUSTIFICATIVA\nFornecedor: Service Tecnologia em Segurança Ltda\n(inversão de ordem cronológica de pagamento)\nEmpenho(s): 5692/2022\nNos termos do art. 5º da Lei Federal nº. 8.666/93 e\nValor: R$ 2.028,00\ninstrução 02/95 item II e aditamento 01/97 do Tribunal de\nAvaré, 05 de julho de 2022\nContas do Estado, vem justificar a necessidade de alteração\nJoselyr Benedito Costa Silvestre\nda ordem cronológica de pagamentos por se tratar de\nPrefeito Municipal\nfornecimento de materiais de limpeza, tal quebra de ordem\nJUSTIFICATIVA\ncronológica se faz necessária para atender a Casa do\n(inversão de ordem cronológica de pagamento)\nCidadão.\nNos termos do art. 5º da Lei Federal nº. 8.666/93 e\nFornecedor: Indústria e Comércio de Produtos de\ninstrução 02/95 item II e aditamento 01/97 do Tribunal de\nLimpeza Macatuba Ltda Me\nContas do Estado, vem justificar a necessidade de alteração\nEmpenho(s): 10572/2022\nda ordem cronológica de pagamentos por se tratar de\nValor: R$ 2.003,54\naquisição de material de informática, tal quebra de ordem\nAvaré, 05 de julho de 2022\ncronológica se faz necessária para atender aos serviços\nSandra de Fátima Theodoro\n1\nEstância Turística de Avaré – Estado de São Paulo\nInstituído pela Lei nº 37, de 28 de março de 2001 e Decreto nº 5.057, de 03 de janeiro de 2018\nSemanário Oficial assinado digitalmente conforme MP nº 2.200-2, de 2001, garantindo autenticidade, validade jurídica e integridade.\n\nSEMANÁRIO\nOficial Eletrônico\navare.sp.gov.br\nTerça-feira, 05 de julho de 2022 Ano VI | Edição nº 1328 Prefeito: Joselyr B. Costa Silvestre\nadministrativos.\nFornecedor: Megadata Indústria e Comércio de\nProdutos\nEmpenho(s): 10434/2022\nValor: R$ 245,00\nAvaré, 05 de julho de 2022\nPatricia de Cassia Furno Olindo Franzolin\nSecretária Municipal de Governo\nJUSTIFICATIVA\n(inversão de ordem cronológica de pagamento)\nNos termos do art. 5º da Lei Federal nº. 8.666/93 e\ninstrução 02/95 item II e aditamento 01/97 do Tribunal de\nContas do Estado, vem justificar a necessidade de alteração\nda ordem cronológica de pagamentos por se tratar de\naquisição de peças para veículo e tal quebra de ordem\ncronológica se faz necessária para manutenção da frota\nmunicipal.\nFornecedor: C. R. Service e Comércio de Produtos e\nPeças em Geral Eireli\nEmpenho(s): 10614,10616,10848,10880/2022\nValor: R$ 10.637,88\nAvaré, 05 de julho de 2022\nCesar Augusto Luciano Franco Morelli\nSecretário Municipal de Transportes e Serviços\nJUSTIFICATIVA\n(inversão de ordem cronológica de pagamento)\nNos termos do art. 5º da Lei Federal nº. 8.666/93 e\ninstrução 02/95 item II e aditamento 01/97 do Tribunal de\nContas do Estado, vem justificar a necessidade de alteração\nda ordem cronológica de pagamentos por se tratar de\naquisição de porta naval com fechadura e ferragens e tal\nquebra de ordem cronológica se faz necessária para\natender as necessidades do Departamento de\nContabilidade.\nFornecedor: Diego Leone\nEmpenho(s): 10849/2022\nValor: R$ 850,00\nAvaré, 05 de julho de 2022\nItamar de Araujo\nSecretário Municipal da Fazenda\nJUSTIFICATIVA\n(inversão de ordem cronológica de pagamento)\nNos termos do art. 5º da Lei Federal nº. 8.666/93 e\ninstrução 02/95 item II e aditamento 01/97 do Tribunal de\nContas do Estado, vem justificar a necessidade de alteração\nda ordem cronológica de pagamentos por se tratar de\naquisição de peças para veículo e tal quebra de ordem\ncronológica se faz necessária para manutenção de veículos\nda frota municipal.\nFornecedor: Chaguri Automotiva Eireli ME\nEmpenho(s): 13127,13128,13129,13130,13131/2022\nValor: R$ 16.211,80\nAvaré, 05 de julho de 2022\nCesar Augusto Luciano Franco Morelli\nSecretário Municipal de Transportes e Serviços\n...........................................................................................................\n2\nEstância Turística de Avaré – Estado de São Paulo\nInstituído pela Lei nº 37, de 28 de março de 2001 e Decreto nº 5.057, de 03 de janeiro de 2018\nSemanário Oficial assinado digitalmente conforme MP nº 2.200-2, de 2001, garantindo autenticidade, validade jurídica e integridade."
}